{"title":"meta_leaks_part_1 : Free Download, Borrow, and Streaming : Internet Archive","lang":"en","content":"<div id=\"readability-page-1\" class=\"page\"><div id=\"maincontent\">\n            <section>\n      <p itemprop=\"interactionStatistic\" itemscope=\"\" itemtype=\"http://schema.org/InteractionCounter\">\n                  \n        \n        <span itemprop=\"userInteractionCount\">0</span>\n\n        Views      </p>\n\n      \n\n          </section>\n    \n                                <section>\n      <h2>\n        DOWNLOAD OPTIONS\n      </h2>\n\n      \n                        \n                                <div>\n                        <p>\n                                          DAISY                          \n                          </p><p>For users with print-disabilities</p>\n                      </div>\n                                <div>\n                        <p>\n                                          EPUB                          \n                      </p></div>\n                                \n                                \n                                \n                                \n                                \n                                \n                                \n                                \n                                \n                            \n      \n                </section>\n        \n    \n\n              <section>\n      <p>\n        Uploaded by\n                  <a href=\"https://archive.org/details/@icw_nru\">\n            icw_nru          </a>\n        \n                  on <time>August 11, 2025</time>\n              </p>\n    </section>\n          </div></div>","textContent":"\n            \n      \n                  \n        \n        0\n\n        Views      \n\n      \n\n          \n    \n                                \n      \n        DOWNLOAD OPTIONS\n      \n\n      \n                        \n                                \n                        \n                                          DAISY                          \n                          For users with print-disabilities\n                      \n                                \n                        \n                                          EPUB                          \n                      \n                                \n                                \n                                \n                                \n                                \n                                \n                                \n                                \n                                \n                            \n      \n                \n        \n    \n\n              \n      \n        Uploaded by\n                  \n            icw_nru          \n        \n                  on August 11, 2025\n              \n    \n          ","length":1111,"excerpt":"meta_leaks_part_1","siteName":"Internet Archive","url":"https://archive.org/details/meta_leaks_part_1"}